MANIFEST.in
README.md
setup.py
mathstats/__init__.py
mathstats/generate_data.py
mathstats/log_normal_param_est.py
mathstats.egg-info/PKG-INFO
mathstats.egg-info/SOURCES.txt
mathstats.egg-info/dependency_links.txt
mathstats.egg-info/requires.txt
mathstats.egg-info/top_level.txt
mathstats/normaldist/__init__.py
mathstats/normaldist/normal.py
mathstats/normaldist/truncatedskewed/__init__.py
mathstats/normaldist/truncatedskewed/param_est.py