Metadata-Version: 1.1
Name: mathstats
Version: 0.2.6.1
Summary: Statistical functions, goodness-of-fit tests and special and special distributions not implemented in scipy/numpy .
Home-page: https://github.com/ksahlin/mathstats
Author: Kristoffer Sahlin
Author-email: kristoffer.sahlin@scilifelab.se
License: GPLv3
Platform: UNKNOWN
Classifier: Development Status :: 2 - Pre-Alpha
Classifier: Environment :: Console
Classifier: Intended Audience :: Science/Research
Classifier: Natural Language :: English
Classifier: Operating System :: POSIX :: Linux
Classifier: Programming Language :: Python
Classifier: Topic :: Scientific/Engineering :: Bio-Informatics
Classifier: Topic :: Scientific/Engineering :: Mathematics
